vanty/__init__.py
vanty/__main__.py
vanty/_client.py
vanty/admin.py
vanty/ai/__init__.py
vanty/auth.py
vanty/cli.py
vanty/community.py
vanty/config.py
vanty/constants.py
vanty/dev.py
vanty/project.py
vanty/scaffold/__init__.py
vanty/scaffold/docs/generator/dialog.md
vanty/scaffold/docs/generator/form.md
vanty/scaffold/docs/generator/vue-shadcn.md
vanty/scaffold/startapp.py
vanty/scaffold/template/app_template/__init__.py-tpl
vanty/scaffold/template/app_template/admin.py-tpl
vanty/scaffold/template/app_template/api.py-tpl
vanty/scaffold/template/app_template/apps.py-tpl
vanty/scaffold/template/app_template/migrations/__init__.py-tpl
vanty/scaffold/template/app_template/models.py-tpl
vanty/scaffold/template/app_template/schemas.py-tpl
vanty/scaffold/template/app_template/tests/__init__.py-tpl
vanty/scaffold/template/app_template/urls.py-tpl
vanty/scaffold/template/app_template/views.py-tpl
vanty/scaffold/template/app_template.zip
vanty/schema.py
vanty/utils/__init__.py
vanty/utils/console_printer.py
vanty/utils/handlers.py
vanty/web/__init__.py
vanty/web/auth_web.py
vanty-0.0.44.dist-info/LICENSE
vanty-0.0.44.dist-info/METADATA
vanty-0.0.44.dist-info/WHEEL
vanty-0.0.44.dist-info/entry_points.txt
vanty-0.0.44.dist-info/RECORD
