Metadata-Version: 2.1
Name: vanty
Version: 0.0.44
Summary: CLI for installing and managing projects & applications from advantch.com and vanty.ai
License: Unspecified
Author: Themba
Author-email: themba@advantch.com
Requires-Python: >=3.8.1,<4.0
Classifier: License :: Other/Proprietary License
Classifier: Programming Language :: Python :: 3
Classifier: Programming Language :: Python :: 3.9
Classifier: Programming Language :: Python :: 3.10
Classifier: Programming Language :: Python :: 3.11
Classifier: Programming Language :: Python :: 3.12
Requires-Dist: django-environ (>=0.10.0,<=0.11.2)
Requires-Dist: honcho (>=1.1.0)
Requires-Dist: httpx (>=0.24.1,<=0.27.0)
Requires-Dist: pydantic (>=2.2.1,<=2.8.2)
Requires-Dist: rich (>=13.7.1,<14.0.0)
Requires-Dist: sh (>=2.0.4,<3.0.0)
Requires-Dist: toml (>=0.10.2,<0.11.0)
Requires-Dist: typer[all] (>=0.9.0)
